MANIFEST.in
requirements.txt
setup.cfg
setup.py
src/pyocker/__init__.py
src/pyocker/dep.py
src/pyocker/pyocker.py
src/pyocker.egg-info/PKG-INFO
src/pyocker.egg-info/SOURCES.txt
src/pyocker.egg-info/dependency_links.txt
src/pyocker.egg-info/entry_points.txt
src/pyocker.egg-info/requires.txt
src/pyocker.egg-info/top_level.txt
src/pyocker/pyocker_modules/__init__.py
src/pyocker/pyocker_modules/build.py
src/pyocker/pyocker_modules/parse.py
src/pyocker/pyocker_modules/push.py
src/pyocker/pyocker_modules/validate.py