Metadata-Version: 1.1
Name: pyocker
Version: 0.2.4
Summary: Docker Utils with Python
Home-page: https://github.com/AkihikoITOH/docker_tools
Author: ITOH Akihiko
Author-email: UNKNOWN
License: MIT
Platform: UNKNOWN
Classifier: Development Status :: 4 - Beta
Classifier: Environment :: Console
Classifier: Intended Audience :: Developers
Classifier: Operating System :: MacOS :: MacOS X
Classifier: Operating System :: POSIX
Classifier: Programming Language :: Python
